NCParse/__init__.py
NCParse/gcode.py
NCParse/gcodesegment.py
NCParse-1.0.7.dist-info/LICENSE
NCParse-1.0.7.dist-info/METADATA
NCParse-1.0.7.dist-info/WHEEL
NCParse-1.0.7.dist-info/top_level.txt
NCParse-1.0.7.dist-info/RECORD
