Metadata-Version: 2.1
Name: NCParse
Version: 1.0.7
Summary: CNC G and M Code code parseer
Author: Marcus Cymerman
Author-email: mpcymerman@gmail.com
License: UNKNOWN
Keywords: python,CNC,GCode,MCode
Platform: UNKNOWN
Classifier: Programming Language :: Python :: 3
Classifier: Operating System :: Unix
Classifier: Operating System :: MacOS :: MacOS X
Classifier: Operating System :: Microsoft :: Windows
License-File: LICENSE
